paintxt.py
paintxt-1.0.0.dist-info/licenses/LICENSE
paintxt-1.0.0.dist-info/METADATA
paintxt-1.0.0.dist-info/WHEEL
paintxt-1.0.0.dist-info/top_level.txt
paintxt-1.0.0.dist-info/RECORD
